boscoin_base/__init__.py
boscoin_base/address.py
boscoin_base/asset.py
boscoin_base/base58.py
boscoin_base/builder.py
boscoin_base/federation.py
boscoin_base/horizon.py
boscoin_base/keypair.py
boscoin_base/memo.py
boscoin_base/network.py
boscoin_base/operation.py
boscoin_base/transaction.py
boscoin_base/transaction_envelope.py
boscoin_base/utils.py
boscoin_base/stellarxdr/StellarXDR_const.py
boscoin_base/stellarxdr/StellarXDR_pack.py
boscoin_base/stellarxdr/StellarXDR_type.py
boscoin_base/stellarxdr/__init__.py
boscoin_base/stellarxdr/xdrgen.py
boscoin_base-0.1.5.dist-info/DESCRIPTION.rst
boscoin_base-0.1.5.dist-info/METADATA
boscoin_base-0.1.5.dist-info/RECORD
boscoin_base-0.1.5.dist-info/WHEEL
boscoin_base-0.1.5.dist-info/metadata.json
boscoin_base-0.1.5.dist-info/top_level.txt
tests/__init__.py
tests/test_asset.py
tests/test_builder.py
tests/test_envelope.py
tests/test_federation.py
tests/test_horizon.py
tests/test_operation.py
tests/test_transaction.py
tests/test_utils.py
