Metadata-Version: 2.0
Name: boscoin-base
Version: 0.1.5
Summary: boscoin-base in python.
Home-page: http://github.com/jinhwanlazy/py-boscoin-base/
Author: Jinhwan Choi
Author-email: jinhwanlazy@gmail.com
License: Apache
Platform: UNKNOWN
Classifier: Development Status :: 3 - Alpha
Classifier: Intended Audience :: Developers
Classifier: Natural Language :: English
Classifier: License :: OSI Approved :: Apache Software License
Classifier: Operating System :: OS Independent
Classifier: Programming Language :: Python
Classifier: Programming Language :: Python :: 2.7
Classifier: Programming Language :: Python :: 3
Classifier: Programming Language :: Python :: 3.4
Classifier: Programming Language :: Python :: 3.5
Classifier: Topic :: Software Development :: Libraries :: Python Modules
Requires-Dist: SSEClient
Requires-Dist: crc16
Requires-Dist: ed25519
Requires-Dist: mnemonic
Requires-Dist: numpy
Requires-Dist: requests
Requires-Dist: toml
